handshake.v
module handshake(
    input clk,
    input rst_n,

    //interface of source
    input valid_s,
    input [7:0] data_s,
    output ready_s,

    //interface of destination
    input ready_d,
    output valid_d,
    output [7:0] data_d
);

reg valid_tmp;
reg [7:0] data_tmp;
reg ready_s;
wire store;
reg data_d;
reg valid_d;

assign store = valid_s && ~ready_d && ready_s;

always@(posedge clk) begin
    if(!rst_n)
    valid_tmp <= 1'b0;
    else 
    valid_tmp <= valid_tmp ? ~ready_d : store;
end

always@(posedge clk)begin
    if(!rst_n)
    data_tmp <= 8'b0;
    else 
    data_tmp <= store? data_s : data_tmp;
end

always@(posedge clk)begin
    if(!rst_n)
    ready_s <= 1'b1;
    else
    ready_s <= (ready_d) || ((!valid_tmp) && (!store));  //这次没存 而且上次也没存
end

always@(posedge clk)begin
    if(!rst_n)
    valid_d <= 1'b0;
    else if(ready_s && valid_s)
    valid_d <= valid_s;
end

always@(posedge clk)begin
    if(!rst_n)
    data_d <= 8'b0;
    else if(valid_s==1'b0)
    data_d <= data_d;
    else 
    data_d <= ready_s ? data_s : data_tmp;
end

endmodule

handshake_tb.v
`timescale 1ns/1ps
`include "handshake.v"
module handshake_tb;
reg        clk;
reg        rst_n;

reg        valid_s;
reg [7:0]  data_s;
wire       ready_s;

reg        ready_d;
wire       valid_d;
wire [7:0] data_d;

handshake test(
    .clk(clk),
    .rst_n(rst_n),
    //interface of source
    .valid_s(valid_s),
    .data_s(data_s),
    .ready_s(ready_s),

    //interface of destination
    .ready_d(ready_d),
    .valid_d(valid_d),
    .data_d(data_d)
);

initial begin
    clk<=1'b0;
    forever 
    #5 clk=~clk;
end

initial begin
    $dumpfile("handshake_wave.vcd");
    $dumpvars;
end

initial begin
    rst_n=1'b0;
    valid_s<=1'b0;
    ready_d<=1'b0;
    #12 
    rst_n<=1'b1;
    #3
    valid_s<=1'b1;   
    data_s<=8'h08;
    #5
    ready_d<=1'b1;
    #5
    data_s<=8'h35;  
    #10
    data_s<=8'hac;
    #10
    data_s<=8'h98;
    ready_d<=1'b0;
    #10
    ready_d<=1'b1;
    data_s<=8'hee;
    #20
    data_s<=8'h98; 
    ready_d<=1'b0; 
    #10
    data_s<=8'h23;
    ready_d<=1'b1;
    #20
    data_s<=8'haa;
    #10
    data_s<=8'hcd;
    #10
    valid_s<=1'b0;
    data_s<=8'hxx;
    #10
    data_s<=8'h4f;
    valid_s<=1'b1;
    #10
    data_s<=8'hac;
    #10
    data_s<=8'hee;
    #3
    ready_d<=1'b0;
    #7
    data_s<=8'h37;
    #4
    ready_d<=1'b1;
    #16
    data_s<=8'h10;
    #50
    $finish;
end

endmodule

handshake_wave.vcd
$date
	Fri May 06 11:17:15 2022
$end
$version
	Icarus Verilog
$end
$timescale
	1ps
$end
$scope module handshake_tb $end
$var wire 1 ! valid_d $end
$var wire 1 " ready_s $end
$var wire 8 # data_d [7:0] $end
$var reg 1 $ clk $end
$var reg 8 % data_s [7:0] $end
$var reg 1 & ready_d $end
$var reg 1 ' rst_n $end
$var reg 1 ( valid_s $end
$scope module test $end
$var wire 1 $ clk $end
$var wire 8 ) data_s [7:0] $end
$var wire 1 & ready_d $end
$var wire 1 ' rst_n $end
$var wire 1 * store $end
$var wire 1 ( valid_s $end
$var wire 1 ! valid_d $end
$var reg 8 + data_d [7:0] $end
$var reg 8 , data_tmp [7:0] $end
$var reg 1 " ready_s $end
$var reg 1 - valid_tmp $end
$upscope $end
$upscope $end
$enddefinitions $end
#0
$dumpvars
x-
bx ,
bx +
0*
bx )
0(
0'
0&
bx %
0$
bx #
x"
x!
$end
#5000
0!
0-
b0 ,
1"
b0 #
b0 +
1$
#10000
0$
#12000
1'
#15000
1*
1!
b1000 %
b1000 )
1(
1$
#20000
0*
1&
0$
#25000
b110101 %
b110101 )
b1000 #
b1000 +
1$
#30000
0$
#35000
b10101100 %
b10101100 )
b110101 #
b110101 +
1$
#40000
0$
#45000
1*
0&
b10011000 %
b10011000 )
b10101100 #
b10101100 +
1$
#50000
0$
#55000
0*
0"
b10011000 ,
1-
b11101110 %
b11101110 )
1&
b10011000 #
b10011000 +
1$
#60000
0$
#65000
0-
1"
1$
#70000
0$
#75000
1*
0&
b10011000 %
b10011000 )
b11101110 #
b11101110 +
1$
#80000
0$
#85000
0*
1-
0"
1&
b100011 %
b100011 )
b10011000 #
b10011000 +
1$
#90000
0$
#95000
1"
0-
1$
#100000
0$
#105000
b10101010 %
b10101010 )
b100011 #
b100011 +
1$
#110000
0$
#115000
b11001101 %
b11001101 )
b10101010 #
b10101010 +
1$
#120000
0$
#125000
0!
bx %
bx )
0(
b11001101 #
b11001101 +
1$
#130000
0$
#135000
1!
1(
b1001111 %
b1001111 )
1$
#140000
0$
#145000
b10101100 %
b10101100 )
b1001111 #
b1001111 +
1$
#150000
0$
#155000
b11101110 %
b11101110 )
b10101100 #
b10101100 +
1$
#158000
1*
0&
#160000
0$
#165000
0*
1-
b11101110 ,
0"
b110111 %
b110111 )
b11101110 #
b11101110 +
1$
#169000
1&
#170000
0$
#175000
1"
0-
1$
#180000
0$
#185000
b10000 %
b10000 )
b110111 #
b110111 +
1$
#190000
0$
#195000
b10000 #
b10000 +
1$
